FNews/__init__.py
FNews/main.py
FNews-5.1.dist-info/METADATA
FNews-5.1.dist-info/WHEEL
FNews-5.1.dist-info/entry_points.txt
FNews-5.1.dist-info/top_level.txt
FNews-5.1.dist-info/RECORD
