Metadata-Version: 2.1
Name: FNews
Version: 5.1
Requires-Dist: requests
Requires-Dist: beautifulsoup4
Requires-Dist: pandas
